setup.py
assignment5.egg-info/PKG-INFO
assignment5.egg-info/SOURCES.txt
assignment5.egg-info/dependency_links.txt
assignment5.egg-info/not-zip-safe
assignment5.egg-info/top_level.txt
controller/__init__.py
controller/forum_controller.py
controller/friendship.py
controller/healthdata.py
controller/register.py
controller/signin.py
controller/test_cases.py
controller/update_controller.py
controller/user_page.py
model/__init__.py
model/forum_model.py
model/friend.py
model/healthdata.py
model/register.py
model/signin.py
model/update_model.py
model/user_data.py
view/__init__.py
view/health.py
view/posts.py
view/register.py
view/signin.py
view/start.py
view/success.py
view/update_view.py
view/user_profile.py