Metadata-Version: 1.0
Name: assignment5
Version: 1.0
Summary: My first project
Home-page: http://vaibhav_agarwal.com
Author: Vaibhav_Ankush
Author-email: vaibhav16119@iiitd.ac.in
License: GPL
Platform: UNKNOWN
